{
  "bg": 147, 
  "temp": "absolute", 
  "snoozeBG": 77, 
  "timestamp": "2016-05-29T20:53:10.969308", 
  "missing": [
    "duration", 
    "rate"
  ], 
  "reason": "Eventual BG 77<100, setting -2.342U/hr, but 26m left and 0 ~ req 0U/hr: no action required", 
  "eventualBG": 77, 
  "error": "missing required input fields", 
  "input": {
    "reason": "Eventual BG 77<100, setting -2.342U/hr, but 26m left and 0 ~ req 0U/hr: no action required", 
    "bg": 147, 
    "eventualBG": 77, 
    "temp": "absolute", 
    "snoozeBG": 77, 
    "mealAssist": "Off: Carbs: 0 Boluses: 0 ISF: 50.8, Target: 115 Deviation: -59 BGI: -2.13", 
    "tick": "+1"
  }, 
  "mealAssist": "Off: Carbs: 0 Boluses: 0 ISF: 50.8, Target: 115 Deviation: -59 BGI: -2.13", 
  "tick": "+1"
}