{
  "bg": 137, 
  "temp": "absolute", 
  "snoozeBG": 226, 
  "timestamp": "2016-05-16T12:57:52.874351", 
  "missing": [
    "duration", 
    "rate"
  ], 
  "reason": "Eventual BG -90<90, bolus snooze: eventual BG range -90-226, temp 0.65 ~ req 0.65U/hr", 
  "eventualBG": -90, 
  "error": "missing required input fields", 
  "input": {
    "reason": "Eventual BG -90<90, bolus snooze: eventual BG range -90-226, temp 0.65 ~ req 0.65U/hr", 
    "bg": 137, 
    "eventualBG": -90, 
    "temp": "absolute", 
    "snoozeBG": 226, 
    "mealAssist": "Off: Carbs: 45 Boluses: 5 ISF: 50.8, Target: 115 Deviation: 5 BGI: -3.58", 
    "tick": -6
  }, 
  "mealAssist": "Off: Carbs: 45 Boluses: 5 ISF: 50.8, Target: 115 Deviation: 5 BGI: -3.58", 
  "tick": -6
}