{
  "bg": 197, 
  "temp": "absolute", 
  "snoozeBG": 232, 
  "timestamp": "2016-05-30T05:13:10.581491", 
  "missing": [
    "duration", 
    "rate"
  ], 
  "reason": "Eventual BG 27<100, bolus snooze: eventual BG range 27-232, temp 0.55 ~ req 0.53U/hr", 
  "eventualBG": 27, 
  "error": "missing required input fields", 
  "input": {
    "reason": "Eventual BG 27<100, bolus snooze: eventual BG range 27-232, temp 0.55 ~ req 0.53U/hr", 
    "bg": 197, 
    "eventualBG": 27, 
    "temp": "absolute", 
    "snoozeBG": 232, 
    "mealAssist": "Off: Carbs: 15 Boluses: 3.2 ISF: 50.8, Target: 115 Deviation: 8 BGI: -3.71", 
    "tick": -1
  }, 
  "mealAssist": "Off: Carbs: 15 Boluses: 3.2 ISF: 50.8, Target: 115 Deviation: 8 BGI: -3.71", 
  "tick": -1
}