{
  "bg": 253, 
  "temp": "absolute", 
  "snoozeBG": 218, 
  "timestamp": "2016-07-18T20:09:08.548689", 
  "missing": [
    "duration", 
    "rate"
  ], 
  "reason": "Eventual BG 218>=130, temp 2.6 >~ req 2.47U/hr", 
  "eventualBG": 218, 
  "error": "missing required input fields", 
  "input": {
    "reason": "Eventual BG 218>=130, temp 2.6 >~ req 2.47U/hr", 
    "bg": 253, 
    "eventualBG": 218, 
    "temp": "absolute", 
    "snoozeBG": 218, 
    "mealAssist": "Off: Carbs: 0 Boluses: 0 ISF: 84.7, Target: 115 Deviation: 5 BGI: -3.6", 
    "tick": -2
  }, 
  "mealAssist": "Off: Carbs: 0 Boluses: 0 ISF: 84.7, Target: 115 Deviation: 5 BGI: -3.6", 
  "tick": -2
}