[
  {
    "trend_arrow": "FLAT", 
    "system_time": "2016-04-18T21:43:05", 
    "display_time": "2016-04-18T14:43:05", 
    "glucose": 219
  }, 
  {
    "trend_arrow": "45_UP", 
    "system_time": "2016-04-18T21:38:08", 
    "display_time": "2016-04-18T14:38:07", 
    "glucose": 217
  }, 
  {
    "trend_arrow": "45_UP", 
    "system_time": "2016-04-18T21:33:06", 
    "display_time": "2016-04-18T14:33:05", 
    "glucose": 211
  }, 
  {
    "trend_arrow": "45_UP", 
    "system_time": "2016-04-18T21:28:06", 
    "display_time": "2016-04-18T14:28:05", 
    "glucose": 206
  }, 
  {
    "trend_arrow": "45_UP", 
    "system_time": "2016-04-18T21:23:06", 
    "display_time": "2016-04-18T14:23:06", 
    "glucose": 200
  }
]