[
  {
    "trend_arrow": "45_DOWN", 
    "system_time": "2016-04-22T20:02:47", 
    "display_time": "2016-04-22T13:02:46", 
    "glucose": 180
  }, 
  {
    "trend_arrow": "45_DOWN", 
    "system_time": "2016-04-22T19:57:45", 
    "display_time": "2016-04-22T12:57:44", 
    "glucose": 185
  }, 
  {
    "trend_arrow": "45_DOWN", 
    "system_time": "2016-04-22T19:52:43", 
    "display_time": "2016-04-22T12:52:42", 
    "glucose": 191
  }, 
  {
    "trend_arrow": "FLAT", 
    "system_time": "2016-04-22T19:43:07", 
    "display_time": "2016-04-22T12:43:07", 
    "glucose": 207
  }, 
  {
    "trend_arrow": "FLAT", 
    "system_time": "2016-04-22T19:37:45", 
    "display_time": "2016-04-22T12:37:45", 
    "glucose": 209
  }
]