[
  {
    "packet_size": 0, 
    "name": "DataEnd", 
    "date": "2016-03-31T17:25:00", 
    "date_type": "none", 
    "_tell": 1, 
    "op": "0x01"
  }, 
  {
    "packet_size": 6, 
    "name": "SensorCalFactor", 
    "raw": "11-d4-1f-10-12-a8", 
    "date": "2016-03-31T17:20:00", 
    "factor": 4.776, 
    "date_type": "minSpecific", 
    "_tell": 2, 
    "op": "0x0f"
  }, 
  {
    "body": "5f", 
    "packet_size": 5, 
    "amount": 95, 
    "name": "CalBGForGH", 
    "raw": "11-c8-1f-90-5f", 
    "date": "2016-03-31T17:08:00", 
    "date_type": "minSpecific", 
    "_tell": 13, 
    "op": "0x0e"
  }, 
  {
    "name": "GlucoseSensorData", 
    "date_type": "prevTimestamp", 
    "_tell": 9, 
    "sgv": 98, 
    "date": "2016-03-31T17:23:00", 
    "packet_size": 0, 
    "op": 49
  }, 
  {
    "name": "GlucoseSensorData", 
    "date_type": "prevTimestamp", 
    "_tell": 10, 
    "sgv": 114, 
    "date": "2016-03-31T17:18:00", 
    "packet_size": 0, 
    "op": 57
  }, 
  {
    "packet_size": 0, 
    "name": "19-Something", 
    "date": "2016-03-31T17:13:00", 
    "date_type": "prevTimestamp", 
    "_tell": 11, 
    "op": "0x13"
  }
]