[
  {
    "_type": "TempBasalDuration", 
    "duration (min)": 30, 
    "_description": "TempBasalDuration 2016-06-03T16:19:43 head[2], body[0] op[0x16]", 
    "timestamp": "2016-06-03T16:19:43", 
    "_body": "", 
    "_head": "1601", 
    "_date": "6b93104310"
  }, 
  {
    "_type": "TempBasal", 
    "temp": "absolute", 
    "_description": "TempBasal 2016-06-03T16:19:43 head[2], body[1] op[0x33]", 
    "timestamp": "2016-06-03T16:19:43", 
    "_body": "00", 
    "_head": "3322", 
    "rate": 0.85, 
    "_date": "6b93104310"
  }, 
  {
    "_type": "TempBasalDuration", 
    "duration (min)": 30, 
    "_description": "TempBasalDuration 2016-06-03T15:47:43 head[2], body[0] op[0x16]", 
    "timestamp": "2016-06-03T15:47:43", 
    "_body": "", 
    "_head": "1601", 
    "_date": "6baf0f4310"
  }, 
  {
    "_type": "TempBasal", 
    "temp": "absolute", 
    "_description": "TempBasal 2016-06-03T15:47:43 head[2], body[1] op[0x33]", 
    "timestamp": "2016-06-03T15:47:43", 
    "_body": "00", 
    "_head": "334a", 
    "rate": 1.85, 
    "_date": "6baf0f4310"
  }, 
  {
    "_type": "TempBasalDuration", 
    "duration (min)": 30, 
    "_description": "TempBasalDuration 2016-06-03T15:39:45 head[2], body[0] op[0x16]", 
    "timestamp": "2016-06-03T15:39:45", 
    "_body": "", 
    "_head": "1601", 
    "_date": "6da70f4310"
  }, 
  {
    "_type": "TempBasal", 
    "temp": "absolute", 
    "_description": "TempBasal 2016-06-03T15:39:45 head[2], body[1] op[0x33]", 
    "timestamp": "2016-06-03T15:39:45", 
    "_body": "00", 
    "_head": "333e", 
    "rate": 1.55, 
    "_date": "6da70f4310"
  }, 
  {
    "_type": "TempBasalDuration", 
    "duration (min)": 30, 
    "_description": "TempBasalDuration 2016-06-03T15:31:43 head[2], body[0] op[0x16]", 
    "timestamp": "2016-06-03T15:31:43", 
    "_body": "", 
    "_head": "1601", 
    "_date": "6b9f0f4310"
  }, 
  {
    "_type": "TempBasal", 
    "temp": "absolute", 
    "_description": "TempBasal 2016-06-03T15:31:43 head[2], body[1] op[0x33]", 
    "timestamp": "2016-06-03T15:31:43", 
    "_body": "00", 
    "_head": "3328", 
    "rate": 1.0, 
    "_date": "6b9f0f4310"
  }, 
  {
    "_type": "TempBasalDuration", 
    "duration (min)": 30, 
    "_description": "TempBasalDuration 2016-06-03T15:23:43 head[2], body[0] op[0x16]", 
    "timestamp": "2016-06-03T15:23:43", 
    "_body": "", 
    "_head": "1601", 
    "_date": "6b970f4310"
  }, 
  {
    "_type": "TempBasal", 
    "temp": "absolute", 
    "_description": "TempBasal 2016-06-03T15:23:43 head[2], body[1] op[0x33]", 
    "timestamp": "2016-06-03T15:23:43", 
    "_body": "00", 
    "_head": "3364", 
    "rate": 2.5, 
    "_date": "6b970f4310"
  }, 
  {
    "_type": "TempBasalDuration", 
    "duration (min)": 30, 
    "_description": "TempBasalDuration 2016-06-03T15:15:41 head[2], body[0] op[0x16]", 
    "timestamp": "2016-06-03T15:15:41", 
    "_body": "", 
    "_head": "1601", 
    "_date": "698f0f4310"
  }, 
  {
    "_type": "TempBasal", 
    "temp": "absolute", 
    "_description": "TempBasal 2016-06-03T15:15:41 head[2], body[1] op[0x33]", 
    "timestamp": "2016-06-03T15:15:41", 
    "_body": "00", 
    "_head": "3354", 
    "rate": 2.1, 
    "_date": "698f0f4310"
  }, 
  {
    "_type": "TempBasalDuration", 
    "duration (min)": 30, 
    "_description": "TempBasalDuration 2016-06-03T15:11:43 head[2], body[0] op[0x16]", 
    "timestamp": "2016-06-03T15:11:43", 
    "_body": "", 
    "_head": "1601", 
    "_date": "6b8b0f4310"
  }, 
  {
    "_type": "TempBasal", 
    "temp": "absolute", 
    "_description": "TempBasal 2016-06-03T15:11:43 head[2], body[1] op[0x33]", 
    "timestamp": "2016-06-03T15:11:43", 
    "_body": "00", 
    "_head": "3348", 
    "rate": 1.8, 
    "_date": "6b8b0f4310"
  }, 
  {
    "_type": "TempBasalDuration", 
    "duration (min)": 30, 
    "_description": "TempBasalDuration 2016-06-03T15:03:41 head[2], body[0] op[0x16]", 
    "timestamp": "2016-06-03T15:03:41", 
    "_body": "", 
    "_head": "1601", 
    "_date": "69830f4310"
  }, 
  {
    "_type": "TempBasal", 
    "temp": "absolute", 
    "_description": "TempBasal 2016-06-03T15:03:41 head[2], body[1] op[0x33]", 
    "timestamp": "2016-06-03T15:03:41", 
    "_body": "00", 
    "_head": "3336", 
    "rate": 1.35, 
    "_date": "69830f4310"
  }, 
  {
    "_type": "TempBasalDuration", 
    "duration (min)": 30, 
    "_description": "TempBasalDuration 2016-06-03T14:59:43 head[2], body[0] op[0x16]", 
    "timestamp": "2016-06-03T14:59:43", 
    "_body": "", 
    "_head": "1601", 
    "_date": "6bbb0e4310"
  }, 
  {
    "_type": "TempBasal", 
    "temp": "absolute", 
    "_description": "TempBasal 2016-06-03T14:59:43 head[2], body[1] op[0x33]", 
    "timestamp": "2016-06-03T14:59:43", 
    "_body": "00", 
    "_head": "3320", 
    "rate": 0.8, 
    "_date": "6bbb0e4310"
  }, 
  {
    "_type": "TempBasalDuration", 
    "duration (min)": 30, 
    "_description": "TempBasalDuration 2016-06-03T14:47:43 head[2], body[0] op[0x16]", 
    "timestamp": "2016-06-03T14:47:43", 
    "_body": "", 
    "_head": "1601", 
    "_date": "6baf0e4310"
  }, 
  {
    "_type": "TempBasal", 
    "temp": "absolute", 
    "_description": "TempBasal 2016-06-03T14:47:43 head[2], body[1] op[0x33]", 
    "timestamp": "2016-06-03T14:47:43", 
    "_body": "00", 
    "_head": "3300", 
    "rate": 0.0, 
    "_date": "6baf0e4310"
  }, 
  {
    "_type": "TempBasalDuration", 
    "duration (min)": 30, 
    "_description": "TempBasalDuration 2016-06-03T14:31:43 head[2], body[0] op[0x16]", 
    "timestamp": "2016-06-03T14:31:43", 
    "_body": "", 
    "_head": "1601", 
    "_date": "6b9f0e4310"
  }, 
  {
    "_type": "TempBasal", 
    "temp": "absolute", 
    "_description": "TempBasal 2016-06-03T14:31:43 head[2], body[1] op[0x33]", 
    "timestamp": "2016-06-03T14:31:43", 
    "_body": "00", 
    "_head": "3300", 
    "rate": 0.0, 
    "_date": "6b9f0e4310"
  }, 
  {
    "_type": "TempBasalDuration", 
    "duration (min)": 30, 
    "_description": "TempBasalDuration 2016-06-03T14:23:43 head[2], body[0] op[0x16]", 
    "timestamp": "2016-06-03T14:23:43", 
    "_body": "", 
    "_head": "1601", 
    "_date": "6b970e4310"
  }, 
  {
    "_type": "TempBasal", 
    "temp": "absolute", 
    "_description": "TempBasal 2016-06-03T14:23:43 head[2], body[1] op[0x33]", 
    "timestamp": "2016-06-03T14:23:43", 
    "_body": "00", 
    "_head": "331b", 
    "rate": 0.675, 
    "_date": "6b970e4310"
  }, 
  {
    "_type": "TempBasalDuration", 
    "duration (min)": 30, 
    "_description": "TempBasalDuration 2016-06-03T14:19:43 head[2], body[0] op[0x16]", 
    "timestamp": "2016-06-03T14:19:43", 
    "_body": "", 
    "_head": "1601", 
    "_date": "6b930e4310"
  }, 
  {
    "_type": "TempBasal", 
    "temp": "absolute", 
    "_description": "TempBasal 2016-06-03T14:19:43 head[2], body[1] op[0x33]", 
    "timestamp": "2016-06-03T14:19:43", 
    "_body": "00", 
    "_head": "331b", 
    "rate": 0.675, 
    "_date": "6b930e4310"
  }, 
  {
    "_type": "TempBasalDuration", 
    "duration (min)": 30, 
    "_description": "TempBasalDuration 2016-06-03T14:15:41 head[2], body[0] op[0x16]", 
    "timestamp": "2016-06-03T14:15:41", 
    "_body": "", 
    "_head": "1601", 
    "_date": "698f0e4310"
  }, 
  {
    "_type": "TempBasal", 
    "temp": "absolute", 
    "_description": "TempBasal 2016-06-03T14:15:41 head[2], body[1] op[0x33]", 
    "timestamp": "2016-06-03T14:15:41", 
    "_body": "00", 
    "_head": "333c", 
    "rate": 1.5, 
    "_date": "698f0e4310"
  }, 
  {
    "_type": "TempBasalDuration", 
    "duration (min)": 30, 
    "_description": "TempBasalDuration 2016-06-03T14:03:43 head[2], body[0] op[0x16]", 
    "timestamp": "2016-06-03T14:03:43", 
    "_body": "", 
    "_head": "1601", 
    "_date": "6b830e4310"
  }, 
  {
    "_type": "TempBasal", 
    "temp": "absolute", 
    "_description": "TempBasal 2016-06-03T14:03:43 head[2], body[1] op[0x33]", 
    "timestamp": "2016-06-03T14:03:43", 
    "_body": "00", 
    "_head": "331a", 
    "rate": 0.65, 
    "_date": "6b830e4310"
  }, 
  {
    "_type": "TempBasalDuration", 
    "duration (min)": 30, 
    "_description": "TempBasalDuration 2016-06-03T13:55:42 head[2], body[0] op[0x16]", 
    "timestamp": "2016-06-03T13:55:42", 
    "_body": "", 
    "_head": "1601", 
    "_date": "6ab70d4310"
  }, 
  {
    "_type": "TempBasal", 
    "temp": "absolute", 
    "_description": "TempBasal 2016-06-03T13:55:42 head[2], body[1] op[0x33]", 
    "timestamp": "2016-06-03T13:55:42", 
    "_body": "00", 
    "_head": "3378", 
    "rate": 3.0, 
    "_date": "6ab70d4310"
  }, 
  {
    "_type": "TempBasalDuration", 
    "duration (min)": 30, 
    "_description": "TempBasalDuration 2016-06-03T13:51:43 head[2], body[0] op[0x16]", 
    "timestamp": "2016-06-03T13:51:43", 
    "_body": "", 
    "_head": "1601", 
    "_date": "6bb30d4310"
  }, 
  {
    "_type": "TempBasal", 
    "temp": "absolute", 
    "_description": "TempBasal 2016-06-03T13:51:43 head[2], body[1] op[0x33]", 
    "timestamp": "2016-06-03T13:51:43", 
    "_body": "00", 
    "_head": "3378", 
    "rate": 3.0, 
    "_date": "6bb30d4310"
  }, 
  {
    "_type": "Bolus", 
    "_description": "Bolus 2016-06-03T13:42:25 head[4], body[0] op[0x01]", 
    "timestamp": "2016-06-03T13:42:25", 
    "_body": "", 
    "appended": [
      {
        "_type": "UnabsorbedInsulinBolus", 
        "_description": "UnabsorbedInsulinBolus unknown head[17], body[0] op[0x5c]", 
        "data": [
          {
            "amount": 2.3, 
            "age": 19
          }, 
          {
            "amount": 1.5, 
            "age": 29
          }, 
          {
            "amount": 2.7, 
            "age": 49
          }, 
          {
            "amount": 1.0, 
            "age": 239
          }, 
          {
            "amount": 5.6, 
            "age": 289
          }
        ], 
        "_body": "", 
        "_head": "5c115c13c03c1dc06c31c028efc0e021d0", 
        "_date": ""
      }
    ], 
    "programmed": 2.7, 
    "_head": "011b1b00", 
    "amount": 2.7, 
    "duration": 0, 
    "type": "normal", 
    "_date": "59aa4d0310"
  }, 
  {
    "_type": "BolusWizard", 
    "bg": 0, 
    "bg_target_high": 130, 
    "correction_estimate": 0.0, 
    "unknown_byte[10]": 0, 
    "_description": "BolusWizard 2016-06-03T13:42:25 head[2], body[13] op[0x5b]", 
    "timestamp": "2016-06-03T13:42:25", 
    "_body": "1950093264001b000000001b82", 
    "carb_input": 25, 
    "_head": "5b00", 
    "unabsorbed_insulin_total": 0.0, 
    "_byte[5]": 0, 
    "unabsorbed_insulin_count": "??", 
    "_byte[7]": 0, 
    "_date": "59aa0d0310", 
    "bolus_estimate": 2.7, 
    "unknown_byte[8]": 0, 
    "carb_ratio": 9, 
    "food_estimate": 2.7, 
    "bg_target_low": 100, 
    "sensitivity": 50
  }, 
  {
    "_type": "TempBasalDuration", 
    "duration (min)": 30, 
    "_description": "TempBasalDuration 2016-06-03T13:31:41 head[2], body[0] op[0x16]", 
    "timestamp": "2016-06-03T13:31:41", 
    "_body": "", 
    "_head": "1601", 
    "_date": "699f0d4310"
  }, 
  {
    "_type": "TempBasal", 
    "temp": "absolute", 
    "_description": "TempBasal 2016-06-03T13:31:41 head[2], body[1] op[0x33]", 
    "timestamp": "2016-06-03T13:31:41", 
    "_body": "00", 
    "_head": "331a", 
    "rate": 0.65, 
    "_date": "699f0d4310"
  }, 
  {
    "_type": "Bolus", 
    "_description": "Bolus 2016-06-03T13:22:00 head[4], body[0] op[0x01]", 
    "timestamp": "2016-06-03T13:22:00", 
    "_body": "", 
    "appended": [
      {
        "_type": "UnabsorbedInsulinBolus", 
        "_description": "UnabsorbedInsulinBolus unknown head[11], body[0] op[0x5c]", 
        "data": [
          {
            "amount": 2.7, 
            "age": 28
          }, 
          {
            "amount": 1.0, 
            "age": 218
          }, 
          {
            "amount": 5.6, 
            "age": 268
          }
        ], 
        "_body": "", 
        "_head": "5c0b6c1cc028dac0e00cd0", 
        "_date": ""
      }
    ], 
    "programmed": 3.8, 
    "_head": "01262600", 
    "amount": 3.8, 
    "duration": 0, 
    "type": "normal", 
    "_date": "40964d0310"
  }, 
  {
    "_type": "BolusWizard", 
    "bg": 0, 
    "bg_target_high": 130, 
    "correction_estimate": 0.0, 
    "unknown_byte[10]": 0, 
    "_description": "BolusWizard 2016-06-03T13:21:59 head[2], body[13] op[0x5b]", 
    "timestamp": "2016-06-03T13:21:59", 
    "_body": "23500932640026000000002682", 
    "carb_input": 35, 
    "_head": "5b00", 
    "unabsorbed_insulin_total": 0.0, 
    "_byte[5]": 0, 
    "unabsorbed_insulin_count": "??", 
    "_byte[7]": 0, 
    "_date": "7b950d0310", 
    "bolus_estimate": 3.8, 
    "unknown_byte[8]": 0, 
    "carb_ratio": 9, 
    "food_estimate": 3.8, 
    "bg_target_low": 100, 
    "sensitivity": 50
  }, 
  {
    "_type": "TempBasalDuration", 
    "duration (min)": 30, 
    "_description": "TempBasalDuration 2016-06-03T13:11:43 head[2], body[0] op[0x16]", 
    "timestamp": "2016-06-03T13:11:43", 
    "_body": "", 
    "_head": "1601", 
    "_date": "6b8b0d4310"
  }, 
  {
    "_type": "TempBasal", 
    "temp": "absolute", 
    "_description": "TempBasal 2016-06-03T13:11:43 head[2], body[1] op[0x33]", 
    "timestamp": "2016-06-03T13:11:43", 
    "_body": "00", 
    "_head": "331a", 
    "rate": 0.65, 
    "_date": "6b8b0d4310"
  }, 
  {
    "_type": "TempBasalDuration", 
    "duration (min)": 30, 
    "_description": "TempBasalDuration 2016-06-03T13:07:43 head[2], body[0] op[0x16]", 
    "timestamp": "2016-06-03T13:07:43", 
    "_body": "", 
    "_head": "1601", 
    "_date": "6b870d4310"
  }, 
  {
    "_type": "TempBasal", 
    "temp": "absolute", 
    "_description": "TempBasal 2016-06-03T13:07:43 head[2], body[1] op[0x33]", 
    "timestamp": "2016-06-03T13:07:43", 
    "_body": "00", 
    "_head": "334a", 
    "rate": 1.85, 
    "_date": "6b870d4310"
  }, 
  {
    "_type": "TempBasalDuration", 
    "duration (min)": 30, 
    "_description": "TempBasalDuration 2016-06-03T13:03:43 head[2], body[0] op[0x16]", 
    "timestamp": "2016-06-03T13:03:43", 
    "_body": "", 
    "_head": "1601", 
    "_date": "6b830d4310"
  }, 
  {
    "_type": "TempBasal", 
    "temp": "absolute", 
    "_description": "TempBasal 2016-06-03T13:03:43 head[2], body[1] op[0x33]", 
    "timestamp": "2016-06-03T13:03:43", 
    "_body": "00", 
    "_head": "3348", 
    "rate": 1.8, 
    "_date": "6b830d4310"
  }, 
  {
    "_type": "TempBasalDuration", 
    "duration (min)": 30, 
    "_description": "TempBasalDuration 2016-06-03T12:59:47 head[2], body[0] op[0x16]", 
    "timestamp": "2016-06-03T12:59:47", 
    "_body": "", 
    "_head": "1601", 
    "_date": "6fbb0c4310"
  }, 
  {
    "_type": "TempBasal", 
    "temp": "absolute", 
    "_description": "TempBasal 2016-06-03T12:59:47 head[2], body[1] op[0x33]", 
    "timestamp": "2016-06-03T12:59:47", 
    "_body": "00", 
    "_head": "333c", 
    "rate": 1.5, 
    "_date": "6fbb0c4310"
  }, 
  {
    "_type": "Bolus", 
    "_description": "Bolus 2016-06-03T12:57:35 head[4], body[0] op[0x01]", 
    "timestamp": "2016-06-03T12:57:35", 
    "_body": "", 
    "appended": [
      {
        "_type": "UnabsorbedInsulinBolus", 
        "_description": "UnabsorbedInsulinBolus unknown head[8], body[0] op[0x5c]", 
        "data": [
          {
            "amount": 1.0, 
            "age": 194
          }, 
          {
            "amount": 5.6, 
            "age": 244
          }
        ], 
        "_body": "", 
        "_head": "5c0828c2c0e0f4c0", 
        "_date": ""
      }
    ], 
    "programmed": 2.7, 
    "_head": "011b1b00", 
    "amount": 2.7, 
    "duration": 0, 
    "type": "normal", 
    "_date": "63b94c0310"
  }, 
  {
    "_type": "BolusWizard", 
    "bg": 0, 
    "bg_target_high": 130, 
    "correction_estimate": 0.0, 
    "unknown_byte[10]": 0, 
    "_description": "BolusWizard 2016-06-03T12:57:35 head[2], body[13] op[0x5b]", 
    "timestamp": "2016-06-03T12:57:35", 
    "_body": "1950093264001b000000001b82", 
    "carb_input": 25, 
    "_head": "5b00", 
    "unabsorbed_insulin_total": 0.0, 
    "_byte[5]": 0, 
    "unabsorbed_insulin_count": "??", 
    "_byte[7]": 0, 
    "_date": "63b90c0310", 
    "bolus_estimate": 2.7, 
    "unknown_byte[8]": 0, 
    "carb_ratio": 9, 
    "food_estimate": 2.7, 
    "bg_target_low": 100, 
    "sensitivity": 50
  }, 
  {
    "_type": "TempBasalDuration", 
    "duration (min)": 30, 
    "_description": "TempBasalDuration 2016-06-03T12:55:41 head[2], body[0] op[0x16]", 
    "timestamp": "2016-06-03T12:55:41", 
    "_body": "", 
    "_head": "1601", 
    "_date": "69b70c4310"
  }, 
  {
    "_type": "TempBasal", 
    "temp": "absolute", 
    "_description": "TempBasal 2016-06-03T12:55:41 head[2], body[1] op[0x33]", 
    "timestamp": "2016-06-03T12:55:41", 
    "_body": "00", 
    "_head": "332a", 
    "rate": 1.05, 
    "_date": "69b70c4310"
  }, 
  {
    "_type": "TempBasalDuration", 
    "duration (min)": 30, 
    "_description": "TempBasalDuration 2016-06-03T12:47:43 head[2], body[0] op[0x16]", 
    "timestamp": "2016-06-03T12:47:43", 
    "_body": "", 
    "_head": "1601", 
    "_date": "6baf0c4310"
  }, 
  {
    "_type": "TempBasal", 
    "temp": "absolute", 
    "_description": "TempBasal 2016-06-03T12:47:43 head[2], body[1] op[0x33]", 
    "timestamp": "2016-06-03T12:47:43", 
    "_body": "00", 
    "_head": "332a", 
    "rate": 1.05, 
    "_date": "6baf0c4310"
  }, 
  {
    "_type": "TempBasalDuration", 
    "duration (min)": 30, 
    "_description": "TempBasalDuration 2016-06-03T12:43:43 head[2], body[0] op[0x16]", 
    "timestamp": "2016-06-03T12:43:43", 
    "_body": "", 
    "_head": "1601", 
    "_date": "6bab0c4310"
  }, 
  {
    "_type": "TempBasal", 
    "temp": "absolute", 
    "_description": "TempBasal 2016-06-03T12:43:43 head[2], body[1] op[0x33]", 
    "timestamp": "2016-06-03T12:43:43", 
    "_body": "00", 
    "_head": "3334", 
    "rate": 1.3, 
    "_date": "6bab0c4310"
  }, 
  {
    "_type": "TempBasalDuration", 
    "duration (min)": 30, 
    "_description": "TempBasalDuration 2016-06-03T12:39:43 head[2], body[0] op[0x16]", 
    "timestamp": "2016-06-03T12:39:43", 
    "_body": "", 
    "_head": "1601", 
    "_date": "6ba70c4310"
  }, 
  {
    "_type": "TempBasal", 
    "temp": "absolute", 
    "_description": "TempBasal 2016-06-03T12:39:43 head[2], body[1] op[0x33]", 
    "timestamp": "2016-06-03T12:39:43", 
    "_body": "00", 
    "_head": "331a", 
    "rate": 0.65, 
    "_date": "6ba70c4310"
  }, 
  {
    "_type": "TempBasalDuration", 
    "duration (min)": 30, 
    "_description": "TempBasalDuration 2016-06-03T12:23:42 head[2], body[0] op[0x16]", 
    "timestamp": "2016-06-03T12:23:42", 
    "_body": "", 
    "_head": "1601", 
    "_date": "6a970c4310"
  }, 
  {
    "_type": "TempBasal", 
    "temp": "absolute", 
    "_description": "TempBasal 2016-06-03T12:23:42 head[2], body[1] op[0x33]", 
    "timestamp": "2016-06-03T12:23:42", 
    "_body": "00", 
    "_head": "3300", 
    "rate": 0.0, 
    "_date": "6a970c4310"
  }, 
  {
    "_type": "TempBasalDuration", 
    "duration (min)": 30, 
    "_description": "TempBasalDuration 2016-06-03T12:19:43 head[2], body[0] op[0x16]", 
    "timestamp": "2016-06-03T12:19:43", 
    "_body": "", 
    "_head": "1601", 
    "_date": "6b930c4310"
  }, 
  {
    "_type": "TempBasal", 
    "temp": "absolute", 
    "_description": "TempBasal 2016-06-03T12:19:43 head[2], body[1] op[0x33]", 
    "timestamp": "2016-06-03T12:19:43", 
    "_body": "00", 
    "_head": "331a", 
    "rate": 0.65, 
    "_date": "6b930c4310"
  }, 
  {
    "_type": "TempBasalDuration", 
    "duration (min)": 30, 
    "_description": "TempBasalDuration 2016-06-03T12:15:38 head[2], body[0] op[0x16]", 
    "timestamp": "2016-06-03T12:15:38", 
    "_body": "", 
    "_head": "1601", 
    "_date": "668f0c4310"
  }, 
  {
    "_type": "TempBasal", 
    "temp": "absolute", 
    "_description": "TempBasal 2016-06-03T12:15:38 head[2], body[1] op[0x33]", 
    "timestamp": "2016-06-03T12:15:38", 
    "_body": "00", 
    "_head": "3325", 
    "rate": 0.925, 
    "_date": "668f0c4310"
  }, 
  {
    "_type": "TempBasalDuration", 
    "duration (min)": 30, 
    "_description": "TempBasalDuration 2016-06-03T12:11:46 head[2], body[0] op[0x16]", 
    "timestamp": "2016-06-03T12:11:46", 
    "_body": "", 
    "_head": "1601", 
    "_date": "6e8b0c4310"
  }, 
  {
    "_type": "TempBasal", 
    "temp": "absolute", 
    "_description": "TempBasal 2016-06-03T12:11:46 head[2], body[1] op[0x33]", 
    "timestamp": "2016-06-03T12:11:46", 
    "_body": "00", 
    "_head": "3325", 
    "rate": 0.925, 
    "_date": "6e8b0c4310"
  }, 
  {
    "_type": "TempBasalDuration", 
    "duration (min)": 30, 
    "_description": "TempBasalDuration 2016-06-03T12:07:41 head[2], body[0] op[0x16]", 
    "timestamp": "2016-06-03T12:07:41", 
    "_body": "", 
    "_head": "1601", 
    "_date": "69870c4310"
  }, 
  {
    "_type": "TempBasal", 
    "temp": "absolute", 
    "_description": "TempBasal 2016-06-03T12:07:41 head[2], body[1] op[0x33]", 
    "timestamp": "2016-06-03T12:07:41", 
    "_body": "00", 
    "_head": "3350", 
    "rate": 2.0, 
    "_date": "69870c4310"
  }, 
  {
    "_type": "TempBasalDuration", 
    "duration (min)": 30, 
    "_description": "TempBasalDuration 2016-06-03T11:55:39 head[2], body[0] op[0x16]", 
    "timestamp": "2016-06-03T11:55:39", 
    "_body": "", 
    "_head": "1601", 
    "_date": "67b70b4310"
  }, 
  {
    "_type": "TempBasal", 
    "temp": "absolute", 
    "_description": "TempBasal 2016-06-03T11:55:39 head[2], body[1] op[0x33]", 
    "timestamp": "2016-06-03T11:55:39", 
    "_body": "00", 
    "_head": "333c", 
    "rate": 1.5, 
    "_date": "67b70b4310"
  }, 
  {
    "_type": "TempBasalDuration", 
    "duration (min)": 30, 
    "_description": "TempBasalDuration 2016-06-03T11:51:41 head[2], body[0] op[0x16]", 
    "timestamp": "2016-06-03T11:51:41", 
    "_body": "", 
    "_head": "1601", 
    "_date": "69b30b4310"
  }, 
  {
    "_type": "TempBasal", 
    "temp": "absolute", 
    "_description": "TempBasal 2016-06-03T11:51:41 head[2], body[1] op[0x33]", 
    "timestamp": "2016-06-03T11:51:41", 
    "_body": "00", 
    "_head": "333c", 
    "rate": 1.5, 
    "_date": "69b30b4310"
  }, 
  {
    "_type": "TempBasalDuration", 
    "duration (min)": 30, 
    "_description": "TempBasalDuration 2016-06-03T11:47:43 head[2], body[0] op[0x16]", 
    "timestamp": "2016-06-03T11:47:43", 
    "_body": "", 
    "_head": "1601", 
    "_date": "6baf0b4310"
  }, 
  {
    "_type": "TempBasal", 
    "temp": "absolute", 
    "_description": "TempBasal 2016-06-03T11:47:43 head[2], body[1] op[0x33]", 
    "timestamp": "2016-06-03T11:47:43", 
    "_body": "00", 
    "_head": "333c", 
    "rate": 1.5, 
    "_date": "6baf0b4310"
  }, 
  {
    "_type": "TempBasalDuration", 
    "duration (min)": 30, 
    "_description": "TempBasalDuration 2016-06-03T11:43:43 head[2], body[0] op[0x16]", 
    "timestamp": "2016-06-03T11:43:43", 
    "_body": "", 
    "_head": "1601", 
    "_date": "6bab0b4310"
  }, 
  {
    "_type": "TempBasal", 
    "temp": "absolute", 
    "_description": "TempBasal 2016-06-03T11:43:43 head[2], body[1] op[0x33]", 
    "timestamp": "2016-06-03T11:43:43", 
    "_body": "00", 
    "_head": "332c", 
    "rate": 1.1, 
    "_date": "6bab0b4310"
  }, 
  {
    "_type": "TempBasalDuration", 
    "duration (min)": 30, 
    "_description": "TempBasalDuration 2016-06-03T11:35:30 head[2], body[0] op[0x16]", 
    "timestamp": "2016-06-03T11:35:30", 
    "_body": "", 
    "_head": "1601", 
    "_date": "5ea30b4310"
  }, 
  {
    "_type": "TempBasal", 
    "temp": "absolute", 
    "_description": "TempBasal 2016-06-03T11:35:30 head[2], body[1] op[0x33]", 
    "timestamp": "2016-06-03T11:35:30", 
    "_body": "00", 
    "_head": "333e", 
    "rate": 1.55, 
    "_date": "5ea30b4310"
  }, 
  {
    "_type": "TempBasalDuration", 
    "duration (min)": 30, 
    "_description": "TempBasalDuration 2016-06-03T11:31:45 head[2], body[0] op[0x16]", 
    "timestamp": "2016-06-03T11:31:45", 
    "_body": "", 
    "_head": "1601", 
    "_date": "6d9f0b4310"
  }, 
  {
    "_type": "TempBasal", 
    "temp": "absolute", 
    "_description": "TempBasal 2016-06-03T11:31:45 head[2], body[1] op[0x33]", 
    "timestamp": "2016-06-03T11:31:45", 
    "_body": "00", 
    "_head": "3354", 
    "rate": 2.1, 
    "_date": "6d9f0b4310"
  }, 
  {
    "_type": "TempBasalDuration", 
    "duration (min)": 30, 
    "_description": "TempBasalDuration 2016-06-03T11:27:36 head[2], body[0] op[0x16]", 
    "timestamp": "2016-06-03T11:27:36", 
    "_body": "", 
    "_head": "1601", 
    "_date": "649b0b4310"
  }, 
  {
    "_type": "TempBasal", 
    "temp": "absolute", 
    "_description": "TempBasal 2016-06-03T11:27:36 head[2], body[1] op[0x33]", 
    "timestamp": "2016-06-03T11:27:36", 
    "_body": "00", 
    "_head": "334e", 
    "rate": 1.95, 
    "_date": "649b0b4310"
  }, 
  {
    "_type": "TempBasalDuration", 
    "duration (min)": 30, 
    "_description": "TempBasalDuration 2016-06-03T11:23:46 head[2], body[0] op[0x16]", 
    "timestamp": "2016-06-03T11:23:46", 
    "_body": "", 
    "_head": "1601", 
    "_date": "6e970b4310"
  }, 
  {
    "_type": "TempBasal", 
    "temp": "absolute", 
    "_description": "TempBasal 2016-06-03T11:23:46 head[2], body[1] op[0x33]", 
    "timestamp": "2016-06-03T11:23:46", 
    "_body": "00", 
    "_head": "335a", 
    "rate": 2.25, 
    "_date": "6e970b4310"
  }, 
  {
    "_type": "TempBasalDuration", 
    "duration (min)": 30, 
    "_description": "TempBasalDuration 2016-06-03T11:19:40 head[2], body[0] op[0x16]", 
    "timestamp": "2016-06-03T11:19:40", 
    "_body": "", 
    "_head": "1601", 
    "_date": "68930b4310"
  }, 
  {
    "_type": "TempBasal", 
    "temp": "absolute", 
    "_description": "TempBasal 2016-06-03T11:19:40 head[2], body[1] op[0x33]", 
    "timestamp": "2016-06-03T11:19:40", 
    "_body": "00", 
    "_head": "3351", 
    "rate": 2.025, 
    "_date": "68930b4310"
  }, 
  {
    "_type": "TempBasalDuration", 
    "duration (min)": 30, 
    "_description": "TempBasalDuration 2016-06-03T11:15:39 head[2], body[0] op[0x16]", 
    "timestamp": "2016-06-03T11:15:39", 
    "_body": "", 
    "_head": "1601", 
    "_date": "678f0b4310"
  }, 
  {
    "_type": "TempBasal", 
    "temp": "absolute", 
    "_description": "TempBasal 2016-06-03T11:15:39 head[2], body[1] op[0x33]", 
    "timestamp": "2016-06-03T11:15:39", 
    "_body": "00", 
    "_head": "334a", 
    "rate": 1.85, 
    "_date": "678f0b4310"
  }, 
  {
    "_type": "TempBasalDuration", 
    "duration (min)": 30, 
    "_description": "TempBasalDuration 2016-06-03T11:11:41 head[2], body[0] op[0x16]", 
    "timestamp": "2016-06-03T11:11:41", 
    "_body": "", 
    "_head": "1601", 
    "_date": "698b0b4310"
  }, 
  {
    "_type": "TempBasal", 
    "temp": "absolute", 
    "_description": "TempBasal 2016-06-03T11:11:41 head[2], body[1] op[0x33]", 
    "timestamp": "2016-06-03T11:11:41", 
    "_body": "00", 
    "_head": "3341", 
    "rate": 1.625, 
    "_date": "698b0b4310"
  }, 
  {
    "_type": "TempBasalDuration", 
    "duration (min)": 30, 
    "_description": "TempBasalDuration 2016-06-03T11:07:43 head[2], body[0] op[0x16]", 
    "timestamp": "2016-06-03T11:07:43", 
    "_body": "", 
    "_head": "1601", 
    "_date": "6b870b4310"
  }, 
  {
    "_type": "TempBasal", 
    "temp": "absolute", 
    "_description": "TempBasal 2016-06-03T11:07:43 head[2], body[1] op[0x33]", 
    "timestamp": "2016-06-03T11:07:43", 
    "_body": "00", 
    "_head": "3341", 
    "rate": 1.625, 
    "_date": "6b870b4310"
  }, 
  {
    "_type": "TempBasalDuration", 
    "duration (min)": 30, 
    "_description": "TempBasalDuration 2016-06-03T11:03:43 head[2], body[0] op[0x16]", 
    "timestamp": "2016-06-03T11:03:43", 
    "_body": "", 
    "_head": "1601", 
    "_date": "6b830b4310"
  }, 
  {
    "_type": "TempBasal", 
    "temp": "absolute", 
    "_description": "TempBasal 2016-06-03T11:03:43 head[2], body[1] op[0x33]", 
    "timestamp": "2016-06-03T11:03:43", 
    "_body": "00", 
    "_head": "332f", 
    "rate": 1.175, 
    "_date": "6b830b4310"
  }, 
  {
    "_type": "TempBasalDuration", 
    "duration (min)": 30, 
    "_description": "TempBasalDuration 2016-06-03T10:59:42 head[2], body[0] op[0x16]", 
    "timestamp": "2016-06-03T10:59:42", 
    "_body": "", 
    "_head": "1601", 
    "_date": "6abb0a4310"
  }, 
  {
    "_type": "TempBasal", 
    "temp": "absolute", 
    "_description": "TempBasal 2016-06-03T10:59:42 head[2], body[1] op[0x33]", 
    "timestamp": "2016-06-03T10:59:42", 
    "_body": "00", 
    "_head": "335e", 
    "rate": 2.35, 
    "_date": "6abb0a4310"
  }, 
  {
    "_type": "BGReceived", 
    "link": "c25417", 
    "_description": "BGReceived 2016-06-03T10:51:09 head[2], body[3] op[0x3f]", 
    "timestamp": "2016-06-03T10:51:09", 
    "_body": "c25417", 
    "_head": "3f17", 
    "amount": 187, 
    "_date": "49b36a6310"
  }, 
  {
    "_type": "CalBGForPH", 
    "_description": "CalBGForPH 2016-06-03T10:51:09 head[2], body[0] op[0x0a]", 
    "timestamp": "2016-06-03T10:51:09", 
    "_body": "", 
    "_head": "0abb", 
    "amount": 187, 
    "_date": "49b32a6310"
  }, 
  {
    "_type": "TempBasalDuration", 
    "duration (min)": 30, 
    "_description": "TempBasalDuration 2016-06-03T10:47:42 head[2], body[0] op[0x16]", 
    "timestamp": "2016-06-03T10:47:42", 
    "_body": "", 
    "_head": "1601", 
    "_date": "6aaf0a4310"
  }, 
  {
    "_type": "TempBasal", 
    "temp": "absolute", 
    "_description": "TempBasal 2016-06-03T10:47:42 head[2], body[1] op[0x33]", 
    "timestamp": "2016-06-03T10:47:42", 
    "_body": "00", 
    "_head": "331e", 
    "rate": 0.75, 
    "_date": "6aaf0a4310"
  }, 
  {
    "_type": "TempBasalDuration", 
    "duration (min)": 30, 
    "_description": "TempBasalDuration 2016-06-03T10:23:42 head[2], body[0] op[0x16]", 
    "timestamp": "2016-06-03T10:23:42", 
    "_body": "", 
    "_head": "1601", 
    "_date": "6a970a4310"
  }, 
  {
    "_type": "TempBasal", 
    "temp": "absolute", 
    "_description": "TempBasal 2016-06-03T10:23:42 head[2], body[1] op[0x33]", 
    "timestamp": "2016-06-03T10:23:42", 
    "_body": "00", 
    "_head": "3300", 
    "rate": 0.0, 
    "_date": "6a970a4310"
  }, 
  {
    "_type": "TempBasalDuration", 
    "duration (min)": 30, 
    "_description": "TempBasalDuration 2016-06-03T10:19:40 head[2], body[0] op[0x16]", 
    "timestamp": "2016-06-03T10:19:40", 
    "_body": "", 
    "_head": "1601", 
    "_date": "68930a4310"
  }, 
  {
    "_type": "TempBasal", 
    "temp": "absolute", 
    "_description": "TempBasal 2016-06-03T10:19:40 head[2], body[1] op[0x33]", 
    "timestamp": "2016-06-03T10:19:40", 
    "_body": "00", 
    "_head": "3325", 
    "rate": 0.925, 
    "_date": "68930a4310"
  }, 
  {
    "programmed": 1.0, 
    "_type": "Bolus", 
    "type": "normal", 
    "_description": "Bolus 2016-06-03T09:50:33 head[4], body[0] op[0x01]", 
    "duration": 0, 
    "timestamp": "2016-06-03T09:50:33", 
    "_body": "", 
    "_head": "010a0a00", 
    "amount": 1.0, 
    "_date": "61b2490310"
  }, 
  {
    "_type": "TempBasalDuration", 
    "duration (min)": 30, 
    "_description": "TempBasalDuration 2016-06-03T09:31:41 head[2], body[0] op[0x16]", 
    "timestamp": "2016-06-03T09:31:41", 
    "_body": "", 
    "_head": "1601", 
    "_date": "699f094310"
  }, 
  {
    "_type": "TempBasal", 
    "temp": "absolute", 
    "_description": "TempBasal 2016-06-03T09:31:41 head[2], body[1] op[0x33]", 
    "timestamp": "2016-06-03T09:31:41", 
    "_body": "00", 
    "_head": "331e", 
    "rate": 0.75, 
    "_date": "699f094310"
  }, 
  {
    "programmed": 5.6, 
    "_type": "Bolus", 
    "type": "normal", 
    "_description": "Bolus 2016-06-03T08:58:43 head[4], body[0] op[0x01]", 
    "duration": 0, 
    "timestamp": "2016-06-03T08:58:43", 
    "_body": "", 
    "_head": "01383800", 
    "amount": 5.6, 
    "_date": "6bba480310"
  }, 
  {
    "_type": "BolusWizard", 
    "bg": 0, 
    "bg_target_high": 130, 
    "correction_estimate": 0.0, 
    "unknown_byte[10]": 0, 
    "_description": "BolusWizard 2016-06-03T08:58:43 head[2], body[13] op[0x5b]", 
    "timestamp": "2016-06-03T08:58:43", 
    "_body": "2d500832640038000000003882", 
    "carb_input": 45, 
    "_head": "5b00", 
    "unabsorbed_insulin_total": 0.0, 
    "_byte[5]": 0, 
    "unabsorbed_insulin_count": "??", 
    "_byte[7]": 0, 
    "_date": "6bba080310", 
    "bolus_estimate": 5.6, 
    "unknown_byte[8]": 0, 
    "carb_ratio": 8, 
    "food_estimate": 5.6, 
    "bg_target_low": 100, 
    "sensitivity": 50
  }, 
  {
    "_type": "TempBasalDuration", 
    "duration (min)": 30, 
    "_description": "TempBasalDuration 2016-06-03T08:51:43 head[2], body[0] op[0x16]", 
    "timestamp": "2016-06-03T08:51:43", 
    "_body": "", 
    "_head": "1601", 
    "_date": "6bb3084310"
  }, 
  {
    "_type": "TempBasal", 
    "temp": "absolute", 
    "_description": "TempBasal 2016-06-03T08:51:43 head[2], body[1] op[0x33]", 
    "timestamp": "2016-06-03T08:51:43", 
    "_body": "00", 
    "_head": "331e", 
    "rate": 0.75, 
    "_date": "6bb3084310"
  }, 
  {
    "_type": "TempBasalDuration", 
    "duration (min)": 30, 
    "_description": "TempBasalDuration 2016-06-03T08:23:43 head[2], body[0] op[0x16]", 
    "timestamp": "2016-06-03T08:23:43", 
    "_body": "", 
    "_head": "1601", 
    "_date": "6b97084310"
  }, 
  {
    "_type": "TempBasal", 
    "temp": "absolute", 
    "_description": "TempBasal 2016-06-03T08:23:43 head[2], body[1] op[0x33]", 
    "timestamp": "2016-06-03T08:23:43", 
    "_body": "00", 
    "_head": "331e", 
    "rate": 0.75, 
    "_date": "6b97084310"
  }, 
  {
    "_type": "TempBasalDuration", 
    "duration (min)": 30, 
    "_description": "TempBasalDuration 2016-06-03T07:55:56 head[2], body[0] op[0x16]", 
    "timestamp": "2016-06-03T07:55:56", 
    "_body": "", 
    "_head": "1601", 
    "_date": "78b7074310"
  }, 
  {
    "_type": "TempBasal", 
    "temp": "absolute", 
    "_description": "TempBasal 2016-06-03T07:55:56 head[2], body[1] op[0x33]", 
    "timestamp": "2016-06-03T07:55:56", 
    "_body": "00", 
    "_head": "331e", 
    "rate": 0.75, 
    "_date": "78b7074310"
  }, 
  {
    "_type": "TempBasalDuration", 
    "duration (min)": 30, 
    "_description": "TempBasalDuration 2016-06-03T07:23:59 head[2], body[0] op[0x16]", 
    "timestamp": "2016-06-03T07:23:59", 
    "_body": "", 
    "_head": "1601", 
    "_date": "7b97074310"
  }, 
  {
    "_type": "TempBasal", 
    "temp": "absolute", 
    "_description": "TempBasal 2016-06-03T07:23:59 head[2], body[1] op[0x33]", 
    "timestamp": "2016-06-03T07:23:59", 
    "_body": "00", 
    "_head": "331e", 
    "rate": 0.75, 
    "_date": "7b97074310"
  }, 
  {
    "_type": "TempBasalDuration", 
    "duration (min)": 30, 
    "_description": "TempBasalDuration 2016-06-03T07:20:04 head[2], body[0] op[0x16]", 
    "timestamp": "2016-06-03T07:20:04", 
    "_body": "", 
    "_head": "1601", 
    "_date": "4494074310"
  }, 
  {
    "_type": "TempBasal", 
    "temp": "absolute", 
    "_description": "TempBasal 2016-06-03T07:20:04 head[2], body[1] op[0x33]", 
    "timestamp": "2016-06-03T07:20:04", 
    "_body": "00", 
    "_head": "331e", 
    "rate": 0.75, 
    "_date": "4494074310"
  }, 
  {
    "_type": "TempBasalDuration", 
    "duration (min)": 30, 
    "_description": "TempBasalDuration 2016-06-03T06:32:02 head[2], body[0] op[0x16]", 
    "timestamp": "2016-06-03T06:32:02", 
    "_body": "", 
    "_head": "1601", 
    "_date": "42a0064310"
  }, 
  {
    "_type": "TempBasal", 
    "temp": "absolute", 
    "_description": "TempBasal 2016-06-03T06:32:02 head[2], body[1] op[0x33]", 
    "timestamp": "2016-06-03T06:32:02", 
    "_body": "00", 
    "_head": "3316", 
    "rate": 0.55, 
    "_date": "42a0064310"
  }, 
  {
    "_type": "TempBasalDuration", 
    "duration (min)": 30, 
    "_description": "TempBasalDuration 2016-06-03T06:27:59 head[2], body[0] op[0x16]", 
    "timestamp": "2016-06-03T06:27:59", 
    "_body": "", 
    "_head": "1601", 
    "_date": "7b9b064310"
  }, 
  {
    "_type": "TempBasal", 
    "temp": "absolute", 
    "_description": "TempBasal 2016-06-03T06:27:59 head[2], body[1] op[0x33]", 
    "timestamp": "2016-06-03T06:27:59", 
    "_body": "00", 
    "_head": "3336", 
    "rate": 1.35, 
    "_date": "7b9b064310"
  }, 
  {
    "_type": "TempBasalDuration", 
    "duration (min)": 30, 
    "_description": "TempBasalDuration 2016-06-03T06:15:57 head[2], body[0] op[0x16]", 
    "timestamp": "2016-06-03T06:15:57", 
    "_body": "", 
    "_head": "1601", 
    "_date": "798f064310"
  }, 
  {
    "_type": "TempBasal", 
    "temp": "absolute", 
    "_description": "TempBasal 2016-06-03T06:15:57 head[2], body[1] op[0x33]", 
    "timestamp": "2016-06-03T06:15:57", 
    "_body": "00", 
    "_head": "3316", 
    "rate": 0.55, 
    "_date": "798f064310"
  }, 
  {
    "_type": "TempBasalDuration", 
    "duration (min)": 30, 
    "_description": "TempBasalDuration 2016-06-03T06:11:58 head[2], body[0] op[0x16]", 
    "timestamp": "2016-06-03T06:11:58", 
    "_body": "", 
    "_head": "1601", 
    "_date": "7a8b064310"
  }, 
  {
    "_type": "TempBasal", 
    "temp": "absolute", 
    "_description": "TempBasal 2016-06-03T06:11:58 head[2], body[1] op[0x33]", 
    "timestamp": "2016-06-03T06:11:58", 
    "_body": "00", 
    "_head": "3334", 
    "rate": 1.3, 
    "_date": "7a8b064310"
  }, 
  {
    "_type": "TempBasalDuration", 
    "duration (min)": 30, 
    "_description": "TempBasalDuration 2016-06-03T05:47:58 head[2], body[0] op[0x16]", 
    "timestamp": "2016-06-03T05:47:58", 
    "_body": "", 
    "_head": "1601", 
    "_date": "7aaf054310"
  }, 
  {
    "_type": "TempBasal", 
    "temp": "absolute", 
    "_description": "TempBasal 2016-06-03T05:47:58 head[2], body[1] op[0x33]", 
    "timestamp": "2016-06-03T05:47:58", 
    "_body": "00", 
    "_head": "3316", 
    "rate": 0.55, 
    "_date": "7aaf054310"
  }, 
  {
    "_type": "TempBasalDuration", 
    "duration (min)": 30, 
    "_description": "TempBasalDuration 2016-06-03T05:43:59 head[2], body[0] op[0x16]", 
    "timestamp": "2016-06-03T05:43:59", 
    "_body": "", 
    "_head": "1601", 
    "_date": "7bab054310"
  }, 
  {
    "_type": "TempBasal", 
    "temp": "absolute", 
    "_description": "TempBasal 2016-06-03T05:43:59 head[2], body[1] op[0x33]", 
    "timestamp": "2016-06-03T05:43:59", 
    "_body": "00", 
    "_head": "332f", 
    "rate": 1.175, 
    "_date": "7bab054310"
  }, 
  {
    "_type": "TempBasalDuration", 
    "duration (min)": 30, 
    "_description": "TempBasalDuration 2016-06-03T05:24:00 head[2], body[0] op[0x16]", 
    "timestamp": "2016-06-03T05:24:00", 
    "_body": "", 
    "_head": "1601", 
    "_date": "4098054310"
  }, 
  {
    "_type": "TempBasal", 
    "temp": "absolute", 
    "_description": "TempBasal 2016-06-03T05:24:00 head[2], body[1] op[0x33]", 
    "timestamp": "2016-06-03T05:24:00", 
    "_body": "00", 
    "_head": "3316", 
    "rate": 0.55, 
    "_date": "4098054310"
  }, 
  {
    "_type": "TempBasalDuration", 
    "duration (min)": 30, 
    "_description": "TempBasalDuration 2016-06-03T05:19:59 head[2], body[0] op[0x16]", 
    "timestamp": "2016-06-03T05:19:59", 
    "_body": "", 
    "_head": "1601", 
    "_date": "7b93054310"
  }, 
  {
    "_type": "TempBasal", 
    "temp": "absolute", 
    "_description": "TempBasal 2016-06-03T05:19:59 head[2], body[1] op[0x33]", 
    "timestamp": "2016-06-03T05:19:59", 
    "_body": "00", 
    "_head": "3316", 
    "rate": 0.55, 
    "_date": "7b93054310"
  }, 
  {
    "_type": "TempBasalDuration", 
    "duration (min)": 30, 
    "_description": "TempBasalDuration 2016-06-03T05:11:47 head[2], body[0] op[0x16]", 
    "timestamp": "2016-06-03T05:11:47", 
    "_body": "", 
    "_head": "1601", 
    "_date": "6f8b054310"
  }, 
  {
    "_type": "TempBasal", 
    "temp": "absolute", 
    "_description": "TempBasal 2016-06-03T05:11:47 head[2], body[1] op[0x33]", 
    "timestamp": "2016-06-03T05:11:47", 
    "_body": "00", 
    "_head": "332d", 
    "rate": 1.125, 
    "_date": "6f8b054310"
  }, 
  {
    "_type": "TempBasalDuration", 
    "duration (min)": 30, 
    "_description": "TempBasalDuration 2016-06-03T05:03:58 head[2], body[0] op[0x16]", 
    "timestamp": "2016-06-03T05:03:58", 
    "_body": "", 
    "_head": "1601", 
    "_date": "7a83054310"
  }, 
  {
    "_type": "TempBasal", 
    "temp": "absolute", 
    "_description": "TempBasal 2016-06-03T05:03:58 head[2], body[1] op[0x33]", 
    "timestamp": "2016-06-03T05:03:58", 
    "_body": "00", 
    "_head": "3316", 
    "rate": 0.55, 
    "_date": "7a83054310"
  }, 
  {
    "_type": "TempBasalDuration", 
    "duration (min)": 30, 
    "_description": "TempBasalDuration 2016-06-03T04:43:58 head[2], body[0] op[0x16]", 
    "timestamp": "2016-06-03T04:43:58", 
    "_body": "", 
    "_head": "1601", 
    "_date": "7aab044310"
  }, 
  {
    "_type": "TempBasal", 
    "temp": "absolute", 
    "_description": "TempBasal 2016-06-03T04:43:58 head[2], body[1] op[0x33]", 
    "timestamp": "2016-06-03T04:43:58", 
    "_body": "00", 
    "_head": "3316", 
    "rate": 0.55, 
    "_date": "7aab044310"
  }, 
  {
    "_type": "TempBasalDuration", 
    "duration (min)": 30, 
    "_description": "TempBasalDuration 2016-06-03T04:39:58 head[2], body[0] op[0x16]", 
    "timestamp": "2016-06-03T04:39:58", 
    "_body": "", 
    "_head": "1601", 
    "_date": "7aa7044310"
  }, 
  {
    "_type": "TempBasal", 
    "temp": "absolute", 
    "_description": "TempBasal 2016-06-03T04:39:58 head[2], body[1] op[0x33]", 
    "timestamp": "2016-06-03T04:39:58", 
    "_body": "00", 
    "_head": "332f", 
    "rate": 1.175, 
    "_date": "7aa7044310"
  }, 
  {
    "_type": "TempBasalDuration", 
    "duration (min)": 30, 
    "_description": "TempBasalDuration 2016-06-03T04:20:00 head[2], body[0] op[0x16]", 
    "timestamp": "2016-06-03T04:20:00", 
    "_body": "", 
    "_head": "1601", 
    "_date": "4094044310"
  }, 
  {
    "_type": "TempBasal", 
    "temp": "absolute", 
    "_description": "TempBasal 2016-06-03T04:20:00 head[2], body[1] op[0x33]", 
    "timestamp": "2016-06-03T04:20:00", 
    "_body": "00", 
    "_head": "3316", 
    "rate": 0.55, 
    "_date": "4094044310"
  }, 
  {
    "_type": "TempBasalDuration", 
    "duration (min)": 30, 
    "_description": "TempBasalDuration 2016-06-03T04:04:00 head[2], body[0] op[0x16]", 
    "timestamp": "2016-06-03T04:04:00", 
    "_body": "", 
    "_head": "1601", 
    "_date": "4084044310"
  }, 
  {
    "_type": "TempBasal", 
    "temp": "absolute", 
    "_description": "TempBasal 2016-06-03T04:04:00 head[2], body[1] op[0x33]", 
    "timestamp": "2016-06-03T04:04:00", 
    "_body": "00", 
    "_head": "332d", 
    "rate": 1.125, 
    "_date": "4084044310"
  }, 
  {
    "_type": "TempBasalDuration", 
    "duration (min)": 30, 
    "_description": "TempBasalDuration 2016-06-03T03:59:58 head[2], body[0] op[0x16]", 
    "timestamp": "2016-06-03T03:59:58", 
    "_body": "", 
    "_head": "1601", 
    "_date": "7abb034310"
  }, 
  {
    "_type": "TempBasal", 
    "temp": "absolute", 
    "_description": "TempBasal 2016-06-03T03:59:58 head[2], body[1] op[0x33]", 
    "timestamp": "2016-06-03T03:59:58", 
    "_body": "00", 
    "_head": "3316", 
    "rate": 0.55, 
    "_date": "7abb034310"
  }, 
  {
    "_type": "TempBasalDuration", 
    "duration (min)": 30, 
    "_description": "TempBasalDuration 2016-06-03T03:39:59 head[2], body[0] op[0x16]", 
    "timestamp": "2016-06-03T03:39:59", 
    "_body": "", 
    "_head": "1601", 
    "_date": "7ba7034310"
  }, 
  {
    "_type": "TempBasal", 
    "temp": "absolute", 
    "_description": "TempBasal 2016-06-03T03:39:59 head[2], body[1] op[0x33]", 
    "timestamp": "2016-06-03T03:39:59", 
    "_body": "00", 
    "_head": "3316", 
    "rate": 0.55, 
    "_date": "7ba7034310"
  }, 
  {
    "_type": "TempBasalDuration", 
    "duration (min)": 30, 
    "_description": "TempBasalDuration 2016-06-03T03:28:00 head[2], body[0] op[0x16]", 
    "timestamp": "2016-06-03T03:28:00", 
    "_body": "", 
    "_head": "1601", 
    "_date": "409c034310"
  }, 
  {
    "_type": "TempBasal", 
    "temp": "absolute", 
    "_description": "TempBasal 2016-06-03T03:28:00 head[2], body[1] op[0x33]", 
    "timestamp": "2016-06-03T03:28:00", 
    "_body": "00", 
    "_head": "3322", 
    "rate": 0.85, 
    "_date": "409c034310"
  }, 
  {
    "_type": "TempBasalDuration", 
    "duration (min)": 30, 
    "_description": "TempBasalDuration 2016-06-03T03:24:00 head[2], body[0] op[0x16]", 
    "timestamp": "2016-06-03T03:24:00", 
    "_body": "", 
    "_head": "1601", 
    "_date": "4098034310"
  }, 
  {
    "_type": "TempBasal", 
    "temp": "absolute", 
    "_description": "TempBasal 2016-06-03T03:24:00 head[2], body[1] op[0x33]", 
    "timestamp": "2016-06-03T03:24:00", 
    "_body": "00", 
    "_head": "3316", 
    "rate": 0.55, 
    "_date": "4098034310"
  }, 
  {
    "_type": "TempBasalDuration", 
    "duration (min)": 30, 
    "_description": "TempBasalDuration 2016-06-03T03:19:58 head[2], body[0] op[0x16]", 
    "timestamp": "2016-06-03T03:19:58", 
    "_body": "", 
    "_head": "1601", 
    "_date": "7a93034310"
  }, 
  {
    "_type": "TempBasal", 
    "temp": "absolute", 
    "_description": "TempBasal 2016-06-03T03:19:58 head[2], body[1] op[0x33]", 
    "timestamp": "2016-06-03T03:19:58", 
    "_body": "00", 
    "_head": "3322", 
    "rate": 0.85, 
    "_date": "7a93034310"
  }, 
  {
    "_type": "TempBasalDuration", 
    "duration (min)": 30, 
    "_description": "TempBasalDuration 2016-06-03T03:03:59 head[2], body[0] op[0x16]", 
    "timestamp": "2016-06-03T03:03:59", 
    "_body": "", 
    "_head": "1601", 
    "_date": "7b83034310"
  }, 
  {
    "_type": "TempBasal", 
    "temp": "absolute", 
    "_description": "TempBasal 2016-06-03T03:03:59 head[2], body[1] op[0x33]", 
    "timestamp": "2016-06-03T03:03:59", 
    "_body": "00", 
    "_head": "3316", 
    "rate": 0.55, 
    "_date": "7b83034310"
  }, 
  {
    "_type": "TempBasalDuration", 
    "duration (min)": 30, 
    "_description": "TempBasalDuration 2016-06-03T03:00:00 head[2], body[0] op[0x16]", 
    "timestamp": "2016-06-03T03:00:00", 
    "_body": "", 
    "_head": "1601", 
    "_date": "4080034310"
  }, 
  {
    "_type": "TempBasal", 
    "temp": "absolute", 
    "_description": "TempBasal 2016-06-03T03:00:00 head[2], body[1] op[0x33]", 
    "timestamp": "2016-06-03T03:00:00", 
    "_body": "00", 
    "_head": "332d", 
    "rate": 1.125, 
    "_date": "4080034310"
  }, 
  {
    "_type": "TempBasalDuration", 
    "duration (min)": 30, 
    "_description": "TempBasalDuration 2016-06-03T02:51:58 head[2], body[0] op[0x16]", 
    "timestamp": "2016-06-03T02:51:58", 
    "_body": "", 
    "_head": "1601", 
    "_date": "7ab3024310"
  }, 
  {
    "_type": "TempBasal", 
    "temp": "absolute", 
    "_description": "TempBasal 2016-06-03T02:51:58 head[2], body[1] op[0x33]", 
    "timestamp": "2016-06-03T02:51:58", 
    "_body": "00", 
    "_head": "3316", 
    "rate": 0.55, 
    "_date": "7ab3024310"
  }, 
  {
    "_type": "TempBasalDuration", 
    "duration (min)": 30, 
    "_description": "TempBasalDuration 2016-06-03T02:40:00 head[2], body[0] op[0x16]", 
    "timestamp": "2016-06-03T02:40:00", 
    "_body": "", 
    "_head": "1601", 
    "_date": "40a8024310"
  }, 
  {
    "_type": "TempBasal", 
    "temp": "absolute", 
    "_description": "TempBasal 2016-06-03T02:40:00 head[2], body[1] op[0x33]", 
    "timestamp": "2016-06-03T02:40:00", 
    "_body": "00", 
    "_head": "332f", 
    "rate": 1.175, 
    "_date": "40a8024310"
  }, 
  {
    "_type": "TempBasalDuration", 
    "duration (min)": 30, 
    "_description": "TempBasalDuration 2016-06-03T02:35:54 head[2], body[0] op[0x16]", 
    "timestamp": "2016-06-03T02:35:54", 
    "_body": "", 
    "_head": "1601", 
    "_date": "76a3024310"
  }, 
  {
    "_type": "TempBasal", 
    "temp": "absolute", 
    "_description": "TempBasal 2016-06-03T02:35:54 head[2], body[1] op[0x33]", 
    "timestamp": "2016-06-03T02:35:54", 
    "_body": "00", 
    "_head": "3316", 
    "rate": 0.55, 
    "_date": "76a3024310"
  }, 
  {
    "_type": "TempBasalDuration", 
    "duration (min)": 30, 
    "_description": "TempBasalDuration 2016-06-03T02:31:46 head[2], body[0] op[0x16]", 
    "timestamp": "2016-06-03T02:31:46", 
    "_body": "", 
    "_head": "1601", 
    "_date": "6e9f024310"
  }, 
  {
    "_type": "TempBasal", 
    "temp": "absolute", 
    "_description": "TempBasal 2016-06-03T02:31:46 head[2], body[1] op[0x33]", 
    "timestamp": "2016-06-03T02:31:46", 
    "_body": "00", 
    "_head": "3316", 
    "rate": 0.55, 
    "_date": "6e9f024310"
  }, 
  {
    "_type": "TempBasalDuration", 
    "duration (min)": 30, 
    "_description": "TempBasalDuration 2016-06-03T02:28:00 head[2], body[0] op[0x16]", 
    "timestamp": "2016-06-03T02:28:00", 
    "_body": "", 
    "_head": "1601", 
    "_date": "409c024310"
  }, 
  {
    "_type": "TempBasal", 
    "temp": "absolute", 
    "_description": "TempBasal 2016-06-03T02:28:00 head[2], body[1] op[0x33]", 
    "timestamp": "2016-06-03T02:28:00", 
    "_body": "00", 
    "_head": "332a", 
    "rate": 1.05, 
    "_date": "409c024310"
  }, 
  {
    "_type": "TempBasalDuration", 
    "duration (min)": 30, 
    "_description": "TempBasalDuration 2016-06-03T02:23:58 head[2], body[0] op[0x16]", 
    "timestamp": "2016-06-03T02:23:58", 
    "_body": "", 
    "_head": "1601", 
    "_date": "7a97024310"
  }, 
  {
    "_type": "TempBasal", 
    "temp": "absolute", 
    "_description": "TempBasal 2016-06-03T02:23:58 head[2], body[1] op[0x33]", 
    "timestamp": "2016-06-03T02:23:58", 
    "_body": "00", 
    "_head": "3316", 
    "rate": 0.55, 
    "_date": "7a97024310"
  }, 
  {
    "_type": "TempBasalDuration", 
    "duration (min)": 30, 
    "_description": "TempBasalDuration 2016-06-03T02:15:45 head[2], body[0] op[0x16]", 
    "timestamp": "2016-06-03T02:15:45", 
    "_body": "", 
    "_head": "1601", 
    "_date": "6d8f024310"
  }, 
  {
    "_type": "TempBasal", 
    "temp": "absolute", 
    "_description": "TempBasal 2016-06-03T02:15:45 head[2], body[1] op[0x33]", 
    "timestamp": "2016-06-03T02:15:45", 
    "_body": "00", 
    "_head": "3325", 
    "rate": 0.925, 
    "_date": "6d8f024310"
  }, 
  {
    "_type": "TempBasalDuration", 
    "duration (min)": 30, 
    "_description": "TempBasalDuration 2016-06-03T02:08:00 head[2], body[0] op[0x16]", 
    "timestamp": "2016-06-03T02:08:00", 
    "_body": "", 
    "_head": "1601", 
    "_date": "4088024310"
  }, 
  {
    "_type": "TempBasal", 
    "temp": "absolute", 
    "_description": "TempBasal 2016-06-03T02:08:00 head[2], body[1] op[0x33]", 
    "timestamp": "2016-06-03T02:08:00", 
    "_body": "00", 
    "_head": "3316", 
    "rate": 0.55, 
    "_date": "4088024310"
  }, 
  {
    "_type": "TempBasalDuration", 
    "duration (min)": 30, 
    "_description": "TempBasalDuration 2016-06-03T01:51:58 head[2], body[0] op[0x16]", 
    "timestamp": "2016-06-03T01:51:58", 
    "_body": "", 
    "_head": "1601", 
    "_date": "7ab3014310"
  }, 
  {
    "_type": "TempBasal", 
    "temp": "absolute", 
    "_description": "TempBasal 2016-06-03T01:51:58 head[2], body[1] op[0x33]", 
    "timestamp": "2016-06-03T01:51:58", 
    "_body": "00", 
    "_head": "332d", 
    "rate": 1.125, 
    "_date": "7ab3014310"
  }, 
  {
    "_type": "TempBasalDuration", 
    "duration (min)": 30, 
    "_description": "TempBasalDuration 2016-06-03T01:35:54 head[2], body[0] op[0x16]", 
    "timestamp": "2016-06-03T01:35:54", 
    "_body": "", 
    "_head": "1601", 
    "_date": "76a3014310"
  }, 
  {
    "_type": "TempBasal", 
    "temp": "absolute", 
    "_description": "TempBasal 2016-06-03T01:35:54 head[2], body[1] op[0x33]", 
    "timestamp": "2016-06-03T01:35:54", 
    "_body": "00", 
    "_head": "3328", 
    "rate": 1.0, 
    "_date": "76a3014310"
  }, 
  {
    "_type": "TempBasalDuration", 
    "duration (min)": 30, 
    "_description": "TempBasalDuration 2016-06-03T01:31:59 head[2], body[0] op[0x16]", 
    "timestamp": "2016-06-03T01:31:59", 
    "_body": "", 
    "_head": "1601", 
    "_date": "7b9f014310"
  }, 
  {
    "_type": "TempBasal", 
    "temp": "absolute", 
    "_description": "TempBasal 2016-06-03T01:31:59 head[2], body[1] op[0x33]", 
    "timestamp": "2016-06-03T01:31:59", 
    "_body": "00", 
    "_head": "3328", 
    "rate": 1.0, 
    "_date": "7b9f014310"
  }, 
  {
    "_type": "TempBasalDuration", 
    "duration (min)": 30, 
    "_description": "TempBasalDuration 2016-06-03T01:15:58 head[2], body[0] op[0x16]", 
    "timestamp": "2016-06-03T01:15:58", 
    "_body": "", 
    "_head": "1601", 
    "_date": "7a8f014310"
  }, 
  {
    "_type": "TempBasal", 
    "temp": "absolute", 
    "_description": "TempBasal 2016-06-03T01:15:58 head[2], body[1] op[0x33]", 
    "timestamp": "2016-06-03T01:15:58", 
    "_body": "00", 
    "_head": "3322", 
    "rate": 0.85, 
    "_date": "7a8f014310"
  }, 
  {
    "_type": "TempBasalDuration", 
    "duration (min)": 30, 
    "_description": "TempBasalDuration 2016-06-03T01:11:47 head[2], body[0] op[0x16]", 
    "timestamp": "2016-06-03T01:11:47", 
    "_body": "", 
    "_head": "1601", 
    "_date": "6f8b014310"
  }, 
  {
    "_type": "TempBasal", 
    "temp": "absolute", 
    "_description": "TempBasal 2016-06-03T01:11:47 head[2], body[1] op[0x33]", 
    "timestamp": "2016-06-03T01:11:47", 
    "_body": "00", 
    "_head": "331e", 
    "rate": 0.75, 
    "_date": "6f8b014310"
  }, 
  {
    "_type": "TempBasalDuration", 
    "duration (min)": 30, 
    "_description": "TempBasalDuration 2016-06-03T00:51:58 head[2], body[0] op[0x16]", 
    "timestamp": "2016-06-03T00:51:58", 
    "_body": "", 
    "_head": "1601", 
    "_date": "7ab3004310"
  }, 
  {
    "_type": "TempBasal", 
    "temp": "absolute", 
    "_description": "TempBasal 2016-06-03T00:51:58 head[2], body[1] op[0x33]", 
    "timestamp": "2016-06-03T00:51:58", 
    "_body": "00", 
    "_head": "331a", 
    "rate": 0.65, 
    "_date": "7ab3004310"
  }, 
  {
    "_type": "TempBasalDuration", 
    "duration (min)": 30, 
    "_description": "TempBasalDuration 2016-06-03T00:40:00 head[2], body[0] op[0x16]", 
    "timestamp": "2016-06-03T00:40:00", 
    "_body": "", 
    "_head": "1601", 
    "_date": "40a8004310"
  }, 
  {
    "_type": "TempBasal", 
    "temp": "absolute", 
    "_description": "TempBasal 2016-06-03T00:40:00 head[2], body[1] op[0x33]", 
    "timestamp": "2016-06-03T00:40:00", 
    "_body": "00", 
    "_head": "332f", 
    "rate": 1.175, 
    "_date": "40a8004310"
  }, 
  {
    "_type": "TempBasalDuration", 
    "duration (min)": 30, 
    "_description": "TempBasalDuration 2016-06-03T00:07:44 head[2], body[0] op[0x16]", 
    "timestamp": "2016-06-03T00:07:44", 
    "_body": "", 
    "_head": "1601", 
    "_date": "6c87004310"
  }, 
  {
    "_type": "TempBasal", 
    "temp": "absolute", 
    "_description": "TempBasal 2016-06-03T00:07:44 head[2], body[1] op[0x33]", 
    "timestamp": "2016-06-03T00:07:44", 
    "_body": "00", 
    "_head": "332d", 
    "rate": 1.125, 
    "_date": "6c87004310"
  }, 
  {
    "_type": "TempBasalDuration", 
    "duration (min)": 30, 
    "_description": "TempBasalDuration 2016-06-03T00:03:42 head[2], body[0] op[0x16]", 
    "timestamp": "2016-06-03T00:03:42", 
    "_body": "", 
    "_head": "1601", 
    "_date": "6a83004310"
  }, 
  {
    "_type": "TempBasal", 
    "temp": "absolute", 
    "_description": "TempBasal 2016-06-03T00:03:42 head[2], body[1] op[0x33]", 
    "timestamp": "2016-06-03T00:03:42", 
    "_body": "00", 
    "_head": "3316", 
    "rate": 0.55, 
    "_date": "6a83004310"
  }, 
  {
    "_type": "Model522ResultTotals", 
    "_description": "Model522ResultTotals 2016-06-03T00:00:00 head[1], body[41] op[0x6d]", 
    "timestamp": "2016-06-03T00:00:00", 
    "_body": "0500e4d2f502000005c403503902742b006402742b01d04a007c1400280607040200010c00e8000000", 
    "_head": "6d", 
    "_date": "6210"
  }, 
  {
    "_type": "ResultDailyTotal", 
    "_description": "ResultDailyTotal 2016-06-03T00:00:00 head[5], body[0] op[0x07]", 
    "timestamp": "2016-06-03T00:00:00", 
    "_body": "", 
    "valid_date": "2016-06-02", 
    "_head": "07000005c4", 
    "_date": "6210"
  }, 
  {
    "_type": "TempBasalDuration", 
    "duration (min)": 30, 
    "_description": "TempBasalDuration 2016-06-02T23:59:44 head[2], body[0] op[0x16]", 
    "timestamp": "2016-06-02T23:59:44", 
    "_body": "", 
    "_head": "1601", 
    "_date": "6cbb174210"
  }, 
  {
    "_type": "TempBasal", 
    "temp": "absolute", 
    "_description": "TempBasal 2016-06-02T23:59:44 head[2], body[1] op[0x33]", 
    "timestamp": "2016-06-02T23:59:44", 
    "_body": "00", 
    "_head": "3316", 
    "rate": 0.55, 
    "_date": "6cbb174210"
  }, 
  {
    "_type": "TempBasalDuration", 
    "duration (min)": 30, 
    "_description": "TempBasalDuration 2016-06-02T23:55:41 head[2], body[0] op[0x16]", 
    "timestamp": "2016-06-02T23:55:41", 
    "_body": "", 
    "_head": "1601", 
    "_date": "69b7174210"
  }, 
  {
    "_type": "TempBasal", 
    "temp": "absolute", 
    "_description": "TempBasal 2016-06-02T23:55:41 head[2], body[1] op[0x33]", 
    "timestamp": "2016-06-02T23:55:41", 
    "_body": "00", 
    "_head": "332a", 
    "rate": 1.05, 
    "_date": "69b7174210"
  }, 
  {
    "_type": "TempBasalDuration", 
    "duration (min)": 30, 
    "_description": "TempBasalDuration 2016-06-02T23:51:43 head[2], body[0] op[0x16]", 
    "timestamp": "2016-06-02T23:51:43", 
    "_body": "", 
    "_head": "1601", 
    "_date": "6bb3174210"
  }, 
  {
    "_type": "TempBasal", 
    "temp": "absolute", 
    "_description": "TempBasal 2016-06-02T23:51:43 head[2], body[1] op[0x33]", 
    "timestamp": "2016-06-02T23:51:43", 
    "_body": "00", 
    "_head": "332a", 
    "rate": 1.05, 
    "_date": "6bb3174210"
  }, 
  {
    "_type": "TempBasalDuration", 
    "duration (min)": 30, 
    "_description": "TempBasalDuration 2016-06-02T23:47:43 head[2], body[0] op[0x16]", 
    "timestamp": "2016-06-02T23:47:43", 
    "_body": "", 
    "_head": "1601", 
    "_date": "6baf174210"
  }, 
  {
    "_type": "TempBasal", 
    "temp": "absolute", 
    "_description": "TempBasal 2016-06-02T23:47:43 head[2], body[1] op[0x33]", 
    "timestamp": "2016-06-02T23:47:43", 
    "_body": "00", 
    "_head": "334e", 
    "rate": 1.95, 
    "_date": "6baf174210"
  }, 
  {
    "_type": "TempBasalDuration", 
    "duration (min)": 30, 
    "_description": "TempBasalDuration 2016-06-02T23:43:41 head[2], body[0] op[0x16]", 
    "timestamp": "2016-06-02T23:43:41", 
    "_body": "", 
    "_head": "1601", 
    "_date": "69ab174210"
  }, 
  {
    "_type": "TempBasal", 
    "temp": "absolute", 
    "_description": "TempBasal 2016-06-02T23:43:41 head[2], body[1] op[0x33]", 
    "timestamp": "2016-06-02T23:43:41", 
    "_body": "00", 
    "_head": "3358", 
    "rate": 2.2, 
    "_date": "69ab174210"
  }, 
  {
    "_type": "Bolus", 
    "_description": "Bolus 2016-06-02T20:46:49 head[4], body[0] op[0x01]", 
    "timestamp": "2016-06-02T20:46:49", 
    "_body": "", 
    "appended": [
      {
        "_type": "UnabsorbedInsulinBolus", 
        "_description": "UnabsorbedInsulinBolus unknown head[14], body[0] op[0x5c]", 
        "data": [
          {
            "amount": 1.5, 
            "age": 323
          }, 
          {
            "amount": 1.0, 
            "age": 343
          }, 
          {
            "amount": 1.15, 
            "age": 363
          }, 
          {
            "amount": 1.05, 
            "age": 373
          }
        ], 
        "_body": "", 
        "_head": "5c0e3c43d02857d02e6bd02a75d0", 
        "_date": ""
      }
    ], 
    "programmed": 3.3, 
    "_head": "01212100", 
    "amount": 3.3, 
    "duration": 0, 
    "type": "normal", 
    "_date": "71ae540210"
  }, 
  {
    "_type": "BolusWizard", 
    "bg": 0, 
    "bg_target_high": 130, 
    "correction_estimate": 0.0, 
    "unknown_byte[10]": 0, 
    "_description": "BolusWizard 2016-06-02T20:46:49 head[2], body[13] op[0x5b]", 
    "timestamp": "2016-06-02T20:46:49", 
    "_body": "1e500932640021000000002182", 
    "carb_input": 30, 
    "_head": "5b00", 
    "unabsorbed_insulin_total": 0.0, 
    "_byte[5]": 0, 
    "unabsorbed_insulin_count": "??", 
    "_byte[7]": 0, 
    "_date": "71ae140210", 
    "bolus_estimate": 3.3, 
    "unknown_byte[8]": 0, 
    "carb_ratio": 9, 
    "food_estimate": 3.3, 
    "bg_target_low": 100, 
    "sensitivity": 50
  }, 
  {
    "_type": "PumpResume", 
    "_description": "PumpResume 2016-06-02T20:46:35 head[2], body[0] op[0x1f]", 
    "timestamp": "2016-06-02T20:46:35", 
    "_body": "", 
    "_head": "1f00", 
    "_date": "63ae140210"
  }, 
  {
    "_type": "PumpSuspend", 
    "_description": "PumpSuspend 2016-06-02T19:40:26 head[2], body[0] op[0x1e]", 
    "timestamp": "2016-06-02T19:40:26", 
    "_body": "", 
    "_head": "1e00", 
    "_date": "5aa8130210"
  }, 
  {
    "_type": "TempBasalDuration", 
    "duration (min)": 30, 
    "_description": "TempBasalDuration 2016-06-02T18:47:43 head[2], body[0] op[0x16]", 
    "timestamp": "2016-06-02T18:47:43", 
    "_body": "", 
    "_head": "1601", 
    "_date": "6baf124210"
  }, 
  {
    "_type": "TempBasal", 
    "temp": "absolute", 
    "_description": "TempBasal 2016-06-02T18:47:43 head[2], body[1] op[0x33]", 
    "timestamp": "2016-06-02T18:47:43", 
    "_body": "00", 
    "_head": "331a", 
    "rate": 0.65, 
    "_date": "6baf124210"
  }, 
  {
    "_type": "TempBasalDuration", 
    "duration (min)": 30, 
    "_description": "TempBasalDuration 2016-06-02T18:43:42 head[2], body[0] op[0x16]", 
    "timestamp": "2016-06-02T18:43:42", 
    "_body": "", 
    "_head": "1601", 
    "_date": "6aab124210"
  }, 
  {
    "_type": "TempBasal", 
    "temp": "absolute", 
    "_description": "TempBasal 2016-06-02T18:43:42 head[2], body[1] op[0x33]", 
    "timestamp": "2016-06-02T18:43:42", 
    "_body": "00", 
    "_head": "331a", 
    "rate": 0.65, 
    "_date": "6aab124210"
  }, 
  {
    "_type": "TempBasalDuration", 
    "duration (min)": 30, 
    "_description": "TempBasalDuration 2016-06-02T18:39:43 head[2], body[0] op[0x16]", 
    "timestamp": "2016-06-02T18:39:43", 
    "_body": "", 
    "_head": "1601", 
    "_date": "6ba7124210"
  }, 
  {
    "_type": "TempBasal", 
    "temp": "absolute", 
    "_description": "TempBasal 2016-06-02T18:39:43 head[2], body[1] op[0x33]", 
    "timestamp": "2016-06-02T18:39:43", 
    "_body": "00", 
    "_head": "331a", 
    "rate": 0.65, 
    "_date": "6ba7124210"
  }, 
  {
    "_type": "TempBasalDuration", 
    "duration (min)": 30, 
    "_description": "TempBasalDuration 2016-06-02T18:39:43 head[2], body[0] op[0x16]", 
    "timestamp": "2016-06-02T18:39:43", 
    "_body": "", 
    "_head": "1601", 
    "_date": "6ba7124210"
  }, 
  {
    "_type": "TempBasal", 
    "temp": "absolute", 
    "_description": "TempBasal 2016-06-02T18:39:43 head[2], body[1] op[0x33]", 
    "timestamp": "2016-06-02T18:39:43", 
    "_body": "00", 
    "_head": "331a", 
    "rate": 0.65, 
    "_date": "6ba7124210"
  }, 
  {
    "_type": "TempBasalDuration", 
    "duration (min)": 30, 
    "_description": "TempBasalDuration 2016-06-02T18:19:42 head[2], body[0] op[0x16]", 
    "timestamp": "2016-06-02T18:19:42", 
    "_body": "", 
    "_head": "1601", 
    "_date": "6a93124210"
  }, 
  {
    "_type": "TempBasal", 
    "temp": "absolute", 
    "_description": "TempBasal 2016-06-02T18:19:42 head[2], body[1] op[0x33]", 
    "timestamp": "2016-06-02T18:19:42", 
    "_body": "00", 
    "_head": "331a", 
    "rate": 0.65, 
    "_date": "6a93124210"
  }, 
  {
    "_type": "TempBasalDuration", 
    "duration (min)": 30, 
    "_description": "TempBasalDuration 2016-06-02T17:59:44 head[2], body[0] op[0x16]", 
    "timestamp": "2016-06-02T17:59:44", 
    "_body": "", 
    "_head": "1601", 
    "_date": "6cbb114210"
  }, 
  {
    "_type": "TempBasal", 
    "temp": "absolute", 
    "_description": "TempBasal 2016-06-02T17:59:44 head[2], body[1] op[0x33]", 
    "timestamp": "2016-06-02T17:59:44", 
    "_body": "00", 
    "_head": "331a", 
    "rate": 0.65, 
    "_date": "6cbb114210"
  }, 
  {
    "_type": "TempBasalDuration", 
    "duration (min)": 30, 
    "_description": "TempBasalDuration 2016-06-02T17:12:00 head[2], body[0] op[0x16]", 
    "timestamp": "2016-06-02T17:12:00", 
    "_body": "", 
    "_head": "1601", 
    "_date": "408c114210"
  }, 
  {
    "_type": "TempBasal", 
    "temp": "absolute", 
    "_description": "TempBasal 2016-06-02T17:12:00 head[2], body[1] op[0x33]", 
    "timestamp": "2016-06-02T17:12:00", 
    "_body": "00", 
    "_head": "3332", 
    "rate": 1.25, 
    "_date": "408c114210"
  }, 
  {
    "_type": "TempBasalDuration", 
    "duration (min)": 30, 
    "_description": "TempBasalDuration 2016-06-02T17:08:03 head[2], body[0] op[0x16]", 
    "timestamp": "2016-06-02T17:08:03", 
    "_body": "", 
    "_head": "1601", 
    "_date": "4388114210"
  }, 
  {
    "_type": "TempBasal", 
    "temp": "absolute", 
    "_description": "TempBasal 2016-06-02T17:08:03 head[2], body[1] op[0x33]", 
    "timestamp": "2016-06-02T17:08:03", 
    "_body": "00", 
    "_head": "3325", 
    "rate": 0.925, 
    "_date": "4388114210"
  }, 
  {
    "_type": "TempBasalDuration", 
    "duration (min)": 30, 
    "_description": "TempBasalDuration 2016-06-02T16:55:54 head[2], body[0] op[0x16]", 
    "timestamp": "2016-06-02T16:55:54", 
    "_body": "", 
    "_head": "1601", 
    "_date": "76b7104210"
  }, 
  {
    "_type": "TempBasal", 
    "temp": "absolute", 
    "_description": "TempBasal 2016-06-02T16:55:54 head[2], body[1] op[0x33]", 
    "timestamp": "2016-06-02T16:55:54", 
    "_body": "00", 
    "_head": "331a", 
    "rate": 0.65, 
    "_date": "76b7104210"
  }, 
  {
    "_type": "TempBasalDuration", 
    "duration (min)": 30, 
    "_description": "TempBasalDuration 2016-06-02T16:52:00 head[2], body[0] op[0x16]", 
    "timestamp": "2016-06-02T16:52:00", 
    "_body": "", 
    "_head": "1601", 
    "_date": "40b4104210"
  }, 
  {
    "_type": "TempBasal", 
    "temp": "absolute", 
    "_description": "TempBasal 2016-06-02T16:52:00 head[2], body[1] op[0x33]", 
    "timestamp": "2016-06-02T16:52:00", 
    "_body": "00", 
    "_head": "3300", 
    "rate": 0.0, 
    "_date": "40b4104210"
  }, 
  {
    "_type": "Bolus", 
    "_description": "Bolus 2016-06-02T15:27:38 head[4], body[0] op[0x01]", 
    "timestamp": "2016-06-02T15:27:38", 
    "_body": "", 
    "appended": [
      {
        "_type": "UnabsorbedInsulinBolus", 
        "_description": "UnabsorbedInsulinBolus unknown head[20], body[0] op[0x5c]", 
        "data": [
          {
            "amount": 1.0, 
            "age": 24
          }, 
          {
            "amount": 1.15, 
            "age": 44
          }, 
          {
            "amount": 1.05, 
            "age": 54
          }, 
          {
            "amount": 1.8, 
            "age": 334
          }, 
          {
            "amount": 1.6, 
            "age": 404
          }, 
          {
            "amount": 4.3, 
            "age": 414
          }
        ], 
        "_body": "", 
        "_head": "5c142818c02e2cc02a36c0484ed04094d0ac9ed0", 
        "_date": ""
      }
    ], 
    "programmed": 1.5, 
    "_head": "010f0f00", 
    "amount": 1.5, 
    "duration": 0, 
    "type": "normal", 
    "_date": "669b4f0210"
  }, 
  {
    "_type": "BolusWizard", 
    "bg": 245, 
    "bg_target_high": 130, 
    "correction_estimate": 0.7, 
    "unknown_byte[10]": 0, 
    "_description": "BolusWizard 2016-06-02T15:27:38 head[2], body[13] op[0x5b]", 
    "timestamp": "2016-06-02T15:27:38", 
    "_body": "0050093264170000001b000082", 
    "carb_input": 0, 
    "_head": "5bf5", 
    "unabsorbed_insulin_total": 2.7, 
    "_byte[5]": 23, 
    "unabsorbed_insulin_count": "??", 
    "_byte[7]": 0, 
    "_date": "669b0f0210", 
    "bolus_estimate": 0.0, 
    "unknown_byte[8]": 0, 
    "carb_ratio": 9, 
    "food_estimate": 0.0, 
    "bg_target_low": 100, 
    "sensitivity": 50
  }, 
  {
    "_type": "CalBGForPH", 
    "_description": "CalBGForPH 2016-06-02T15:27:24 head[2], body[0] op[0x0a]", 
    "timestamp": "2016-06-02T15:27:24", 
    "_body": "", 
    "_head": "0af5", 
    "amount": 245, 
    "_date": "589b2f0210"
  }, 
  {
    "programmed": 1.0, 
    "_type": "Bolus", 
    "type": "normal", 
    "_description": "Bolus 2016-06-02T15:11:53 head[4], body[0] op[0x01]", 
    "duration": 0, 
    "timestamp": "2016-06-02T15:11:53", 
    "_body": "", 
    "_head": "010a0a00", 
    "amount": 1.0, 
    "_date": "758b4f0210"
  }, 
  {
    "_type": "Bolus", 
    "_description": "Bolus 2016-06-02T14:42:19 head[4], body[0] op[0x01]", 
    "timestamp": "2016-06-02T14:42:19", 
    "_body": "", 
    "appended": [
      {
        "_type": "UnabsorbedInsulinBolus", 
        "_description": "UnabsorbedInsulinBolus unknown head[11], body[0] op[0x5c]", 
        "data": [
          {
            "amount": 1.8, 
            "age": 289
          }, 
          {
            "amount": 1.6, 
            "age": 359
          }, 
          {
            "amount": 4.3, 
            "age": 369
          }
        ], 
        "_body": "", 
        "_head": "5c0b4821d04067d0ac71d0", 
        "_date": ""
      }
    ], 
    "programmed": 2.2, 
    "_head": "01161600", 
    "amount": 2.2, 
    "duration": 0, 
    "type": "normal", 
    "_date": "53aa4e0210"
  }, 
  {
    "_type": "BolusWizard", 
    "bg": 0, 
    "bg_target_high": 130, 
    "correction_estimate": 0.0, 
    "unknown_byte[10]": 0, 
    "_description": "BolusWizard 2016-06-02T14:42:19 head[2], body[13] op[0x5b]", 
    "timestamp": "2016-06-02T14:42:19", 
    "_body": "14500932640016000000001682", 
    "carb_input": 20, 
    "_head": "5b00", 
    "unabsorbed_insulin_total": 0.0, 
    "_byte[5]": 0, 
    "unabsorbed_insulin_count": "??", 
    "_byte[7]": 0, 
    "_date": "53aa0e0210", 
    "bolus_estimate": 2.2, 
    "unknown_byte[8]": 0, 
    "carb_ratio": 9, 
    "food_estimate": 2.2, 
    "bg_target_low": 100, 
    "sensitivity": 50
  }, 
  {
    "_type": "TempBasalDuration", 
    "duration (min)": 30, 
    "_description": "TempBasalDuration 2016-06-02T14:19:43 head[2], body[0] op[0x16]", 
    "timestamp": "2016-06-02T14:19:43", 
    "_body": "", 
    "_head": "1601", 
    "_date": "6b930e4210"
  }, 
  {
    "_type": "TempBasal", 
    "temp": "absolute", 
    "_description": "TempBasal 2016-06-02T14:19:43 head[2], body[1] op[0x33]", 
    "timestamp": "2016-06-02T14:19:43", 
    "_body": "00", 
    "_head": "3368", 
    "rate": 2.6, 
    "_date": "6b930e4210"
  }, 
  {
    "_type": "TempBasalDuration", 
    "duration (min)": 30, 
    "_description": "TempBasalDuration 2016-06-02T12:31:44 head[2], body[0] op[0x16]", 
    "timestamp": "2016-06-02T12:31:44", 
    "_body": "", 
    "_head": "1601", 
    "_date": "6c9f0c4210"
  }, 
  {
    "_type": "TempBasal", 
    "temp": "absolute", 
    "_description": "TempBasal 2016-06-02T12:31:44 head[2], body[1] op[0x33]", 
    "timestamp": "2016-06-02T12:31:44", 
    "_body": "00", 
    "_head": "331a", 
    "rate": 0.65, 
    "_date": "6c9f0c4210"
  }
]